MANIFEST.in
README.md
setup.py
usigtreatment/__init__.py
usigtreatment/umaths.py
usigtreatment/utreatment.py
usigtreatment.egg-info/PKG-INFO
usigtreatment.egg-info/SOURCES.txt
usigtreatment.egg-info/dependency_links.txt
usigtreatment.egg-info/top_level.txt