Metadata-Version: 1.1
Name: usigtreatment
Version: 0.0.1
Summary: Utility functionnalities for signal treatments
Home-page: UNKNOWN
Author: Krounet
Author-email: krounet@gmail.com
License: WTFPL
Platform: UNKNOWN
Classifier: Programming Language :: Python
Classifier: Development Status :: 1 - Planning
Classifier: Natural Language :: French
Classifier: Operating System :: OS Independent
Classifier: Programming Language :: Python :: 2.7
Classifier: Topic :: Scientific/Engineering
